markus_autotest_helpers_notebook/__init__.py
markus_autotest_helpers_notebook/importer/__init__.py
markus_autotest_helpers_notebook/merger/__init__.py
markus_autotest_helpers_notebook/pytest/__init__.py
markus_autotest_helpers_notebook/pytest/notebook_collector_plugin.py
markus_autotest_helpers_notebook-0.1.0.dist-info/WHEEL
markus_autotest_helpers_notebook-0.1.0.dist-info/METADATA
markus_autotest_helpers_notebook-0.1.0.dist-info/RECORD
